Metadata-Version: 2.1
Name: fpGrowthpro
Version: 0.1
Summary: this is fpGrowth
Home-page: https://badwei.xyz/
Author: lxwbadwei
Author-email: 1211304872@qq.com
License: MIT
Platform: UNKNOWN
